common/__init__.py
common/apps.py
common/urls.py
common/views.py
common/apps/__init__.py
common/apps/citizenship_app.py
common/apps/city_app.py
common/apps/country_app.py
common/apps/currency_app.py
common/apps/dashboard.py
common/apps/institution_app.py
common/apps/nationality_app.py
common/fixtures/initial_data.yaml
common/migrations/0001_initial.py
common/migrations/__init__.py
common/models/__init__.py
common/models/citizenship.py
common/models/city.py
common/models/country.py
common/models/currency.py
common/models/institution.py
common/models/nationality.py
core_utils/__init__.py
core_utils/models_functions.py
core_common-0.2.dist-info/METADATA
core_common-0.2.dist-info/WHEEL
core_common-0.2.dist-info/top_level.txt
core_common-0.2.dist-info/RECORD
