Metadata-Version: 2.1
Name: core-common
Version: 0.2
Summary: Research CORE ERM - common module
Home-page: https://github.com/research-core/core-common
Author: Ricardo Ribeiro, Hugo Cachitas
Author-email: ricardojvr@gmail.com, hugo.cachitas@research.fchampalimaud.org
License: MIT
Platform: UNKNOWN
Requires-Dist: pyforms-web
Requires-Dist: notifications-central
Requires-Dist: django (>=2.2)
